insee_pcs/PCS.db
insee_pcs/__init__.py
insee_pcs/_management.py
insee_pcs/main.py
insee_pcs/test_main.py
insee_pcs-0.1.0.dist-info/DESCRIPTION.rst
insee_pcs-0.1.0.dist-info/METADATA
insee_pcs-0.1.0.dist-info/RECORD
insee_pcs-0.1.0.dist-info/WHEEL
insee_pcs-0.1.0.dist-info/metadata.json
insee_pcs-0.1.0.dist-info/top_level.txt
