Metadata-Version: 2.0
Name: insee-pcs
Version: 0.1.0
Summary: A set of tools to use the 'Professions et Catégories Socioprofessionnelles' system of INSEE (a French statistical agency).
Home-page: http://github.com/rezemika/python-insee-pcs
Author: rezemika
Author-email: reze.mika@gmail.com
License: UNKNOWN
Platform: UNKNOWN
Classifier: Programming Language :: Python
Classifier: Programming Language :: Python :: 3
Classifier: License :: OSI Approved :: GNU Affero General Public License v3
Classifier: Operating System :: OS Independent
Classifier: Development Status :: 3 - Alpha
Classifier: Natural Language :: French
Classifier: Topic :: Utilities
Classifier: Topic :: Database
Requires-Dist: peewee
